serialduino/Serialduino.ino
serialduino/__init__.py
serialduino-0.2.dist-info/METADATA
serialduino-0.2.dist-info/WHEEL
serialduino-0.2.dist-info/top_level.txt
serialduino-0.2.dist-info/RECORD
